{"forum": {"content": "\u6b61\u8fce\ud83d\udc4f\ud83d\udc4f\ud83d\udc4f<br />\u4ea4\u53cb\u3001\u63ea\u4eba\u4e00\u8d77\u559d\u5496\u5561\u6253\u50b3\u8aaa<br />\u4ea4\u53cb\u3001\u63ea\u4eba\u4e00\u8d77\u901b\u8857 \u591c\u5e02 \u8ce3\u5834<br />\u5c31\u9019\u9ebc\u7c21\u55ae \u5728\u7c21\u55ae\u4e0d\u904e\u4e86\uff5e<br /><br />\u9664\u4e86\u4e0a\u591c\u5e97/\u516b\u5927/\u9152<br />\u4ee5\u4e0a\u6211\u7121\u6cd5\u53c3\u8207\uff5e", "images": ["http://filestoresg1.beetalkmobile.com:8081/file/9d3d1c9236e4114152c1d3017eab0dba"], "urls": [], "title": "\u53f0\u5357\u4eba\u54ea\u53bb\u4e86\uff1f"}, "threadStatus": 1, "regionId": 886, "barStatus": 0, "barId": 675, "postBy": {"utc": 1534545679000, "level": 2, "location": "\u53f0\u5357\u5e02\u00b7\u53f0\u7063", "avatar": "http://filestoresg1.beetalkmobile.com:8081/file/2", "name": "User blocked"}, "id": 9322326}
