{"forum": {"content": "\u932f\u611b", "images": ["http://filestoresg1.beetalkmobile.com:8081/file/3500dfa2a1d1507350d0636d4f346baa"], "urls": [], "title": "\u5357\u54e5\uff08\u53f0\u7063\u53ea\u6709\u4e00\u500b\u6d69\u5357\uff09"}, "threadStatus": 0, "regionId": 886, "barStatus": 0, "barId": 747, "postBy": {"utc": 1535989313000, "level": 1, "location": "\u53f0\u4e2d\u5e02\u00b7\u53f0\u7063", "avatar": "http://filestoresg1.beetalkmobile.com:8081/file/-5076434171487657266", "name": "\u5357\u54e5"}, "id": 9485940}
