{"forum": {"content": "\ud83d\udc8b\ud83d\udc8b\u4f86\u8a8d\u8b58\u55ce\ud83d\udc8b\ud83d\udc8b", "images": ["http://filestoresg1.beetalkmobile.com:8081/file/44504214e5f4ee2a5688cc0cf128f1c8"], "urls": [], "title": "\u4f86\u8a8d\u8b58\uff1f"}, "threadStatus": 0, "regionId": 886, "barStatus": 0, "barId": 205, "postBy": {"utc": 1532260674000, "level": 2, "location": "\u65b0\u5317\u5e02\u00b7\u53f0\u6e7e", "avatar": "http://filestoresg1.beetalkmobile.com:8081/file/2", "name": "User blocked"}, "id": 9069989}
