{"forum": {"content": "\u8a8d\u8b58\u6843\u5712\u670b\u53cb\uff0c30-35", "images": ["http://filestoresg1.beetalkmobile.com:8081/file/d87449134e7cc3f8d4c1c966dcf54f4b"], "urls": [], "title": "\u8a8d\u8b58\u6843\u5712\u670b\u53cb"}, "threadStatus": 1, "regionId": 886, "barStatus": 0, "barId": 13, "postBy": {"utc": 1535102069000, "level": 1, "location": "\u6843\u5712\u5e02\u00b7\u53f0\u7063", "avatar": "http://filestoresg1.beetalkmobile.com:8081/file/8650890419217742107", "name": "\u7d2b"}, "id": 9383932}
