{"forum": {"content": "\u4e2d\u5e74\u7537\u5b50\u5192\u500b\u6ce1<br />\u6709\u559c\u6b61\u7fbd\u7403\u7684\u55ce\uff1f\ud83c\udff8<br />\u6c92\u6709\u7684\u8a71\u3001\u6211\u660e\u5929\u5728\u554f\ud83d\ude02\ud83d\ude02", "images": ["http://filestoresg1.beetalkmobile.com:8081/file/e39e2300557c550f67673c1a477151ae"], "urls": [], "title": "\u4f5b\u7cfb\ud83d\ude4f\ud83c\udffb"}, "threadStatus": 1, "regionId": 886, "barStatus": 0, "barId": 4, "postBy": {"utc": 1534251479000, "level": 4, "location": "", "avatar": "http://filestoresg1.beetalkmobile.com:8081/file/-3874991223383802363", "name": "Sam"}, "id": 9290623}
