{"forum": {"content": "\u9811\u5f37\u7684\u72c2\u98a8\u88e1\u64c1\u62b1", "images": [], "urls": [{"url": "http://17sing.tw/share_song/index.html?sid=53770413", "thumbUrl": "http://img.17sing.tw/uc/img/head_5398144_1523424214.png", "description": "\u6211\u548c\u0fd4Gigi\u0fc6\u0fd1\u0f7d\u1d19\u018e\u0189\u5408\u5531\u4e86\u4e00\u9996\u300a\u72c2\u98a8\u88e1\u64c1\u62b1(Live)\u300b\uff0c\u5feb\u4f86\u807d\u807d\u5427", "title": "\u6b61\u6b4c\u5206\u4eab"}], "title": "\u72c2\u98a8\u88e1\u64c1\u62b1"}, "threadStatus": 0, "regionId": 886, "barStatus": 0, "barId": 850, "postBy": {"utc": 1538242371000, "level": 1, "location": "\u65b0\u5317\u5e02\u00b7\u53f0\u7063", "avatar": "http://filestoresg1.beetalkmobile.com:8081/file/-357765689258724694", "name": "\u9673\u6137\u658c"}, "id": 9752455}
