{"forum": {"content": "\u6709\u6c92\u6709\u5f70\u5316\u6216\u53f0\u4e2d\u7684\u4eba\u665a\u4e0a\u8981\u4e00\u8d77\u9a0e\u8eca\u901b\u901b<br />\u8d70\u8d70\u671b\u9ad8\u5bee\u6216\u5176\u4ed6\u666f\u9ede<br />\u6216\u662f\u52a0\u500b\u670b\u53cb\u4f86\u804a\u5929\ud83d\ude0a", "images": ["http://filestoresg1.beetalkmobile.com:8081/file/7d13cefcfb7d795a1e83daf679cc5fdb"], "urls": [], "title": "\u88ab\u80cc\u53db\u4e86 \u53ea\u60f3\u627e\u4eba\u8ac7\u5fc3"}, "threadStatus": 0, "regionId": 886, "barStatus": 0, "barId": 205, "postBy": {"utc": 1537901019000, "level": 1, "location": "", "avatar": "http://filestoresg1.beetalkmobile.com:8081/file/-7662883540585603070", "name": "\u53eb\u54f2\u6b38"}, "id": 9710641}
