{"forum": {"content": "5\u6708\u62cd\u651d~", "images": ["http://filestoresg1.beetalkmobile.com:8081/file/aa8f49a3ce8510b9b3942a5136e4ed60", "http://filestoresg1.beetalkmobile.com:8081/file/8f9ce7d95f666982f3091e02e29f5a2a", "http://filestoresg1.beetalkmobile.com:8081/file/d7e2aff00e53276924ccd004c6226bcb", "http://filestoresg1.beetalkmobile.com:8081/file/eef5e468a172ad9bf8e27d51e0e50da7", "http://filestoresg1.beetalkmobile.com:8081/file/d4609b044e18a78b1cd2dcbb6ced0c61", "http://filestoresg1.beetalkmobile.com:8081/file/e20da18bd93e6ec675c35172fcbac7f8"], "urls": [], "title": "\u6de1\u6c34~"}, "threadStatus": 0, "regionId": 886, "barStatus": 0, "barId": 77, "postBy": {"utc": 1532069495000, "level": 16, "location": "", "avatar": "http://filestoresg1.beetalkmobile.com:8081/file/6433167780409076092", "name": "\u6cf0\u8fea"}, "id": 9049296}
