{"forum": {"content": "\u9019\u500b\u7fa4\u7d44\u53ef\u4ee5\u73a9\u904a\u6232 \u4e5f\u53ef\u4ee5\u804a\u5929<br />\u60f3\u8981\u7684\u8a71\u8acb\u7559\u4e0bLINE\u7684lD<br />\u76ee\u524d\u6c92\u6709\u5728\u6536\u4eba\uff0c \u5230\u6642\u5019\u6703\u958b\u653e\u6536\u4eba", "images": ["http://filestoresg1.beetalkmobile.com:8081/file/dcf0262f991921d7c333825d77ad4235"], "urls": [], "title": "\u8ab0\u8981\u52a0"}, "threadStatus": 0, "regionId": 886, "barStatus": 0, "barId": 65, "postBy": {"utc": 1534042408000, "level": 1, "location": "\u65b0\u5317\u5e02\u00b7\u53f0\u7063", "avatar": "http://filestoresg1.beetalkmobile.com:8081/file/-85127484121096821", "name": "\u5433\u5de7\u67d4"}, "id": 9265845}
