{"forum": {"content": "\u6700\u8fd1\u958b\u5b78\u4e86<br />\u6709\u6c92\u6709\u59d0\u59d0\u6216\u59b9\u59b9\u8981\u7d04\u51fa\u4f86\u73a9\u7684", "images": ["http://filestoresg1.beetalkmobile.com:8081/file/3addc30490a9fd5446a1b73051f31ff0", "http://filestoresg1.beetalkmobile.com:8081/file/7caa104efebf25b5ad7f84fb643102ba"], "urls": [], "title": "\u9ad8\u4e00\u751f\u4f86\u4ea4\u670b\u53cb\uff1f"}, "threadStatus": 0, "regionId": 886, "barStatus": 0, "barId": 205, "postBy": {"utc": 1537195191000, "level": 1, "location": "\u53f0\u5357\u5e02\u00b7\u53f0\u7063", "avatar": "http://filestoresg1.beetalkmobile.com:8081/file/806142160005678714", "name": "koalaeilson"}, "id": 9626943}
