{"forum": {"content": "\u5982\u984c <br />\u60f3\u8ac7\u500b\u7c21\u55ae\u7684\u611f\u60c5 \u70ba\u751a\u9ebc\u9019\u9ebc\u96e3\u2026<br />\u70ba\u751a\u9ebc\u5462\u2026<br /><br />\u8ab0\u53ef\u4ee5\u966a\u6211\u8d70\u51fa\u4f86 \u6216\u8a31\u53ea\u80fd\u9760\u81ea\u5df1\u4e86\u2026", "images": ["http://filestoresg1.beetalkmobile.com:8081/file/42f1d6834930dad298d786815c91abef"], "urls": [], "title": "\u8ab0\u4f86\u966a\u6211\u8d70\u51fa\u5931\u6200\u671f \ud83d\ude2d\ud83d\ude2d"}, "threadStatus": 0, "regionId": 886, "barStatus": 0, "barId": 20, "postBy": {"utc": 1538142733000, "level": 7, "location": "\u9ad8\u96c4\u5e02\u00b7\u53f0\u7063", "avatar": "http://filestoresg1.beetalkmobile.com:8081/file/-6979895502207560200", "name": "Nicker"}, "id": 9737767}
