{"forum": {"content": "\u6c5f\u5c71\u6613\u6539\u672c\u6027\u96e3\u79fb<br /><br />\u8a00\u800c\u7121\u4fe1\u7684\u4eba\u4e0d\u53ef\u4ea4<br /><br />\u59cb\u4e82\u7d42\u68c4\u7684\u4eba\u7686\u5f3a\u8bcd\u593a\u7406\u5747\u975e\u6b63\u8bba\u4e0d\u5fc5\u518d\u8a00", "images": ["http://filestoresg1.beetalkmobile.com:8081/file/83e1820ee76fd03a0ed7c67c5aafe0d5"], "urls": [], "title": "\u7d55\u671b\u770b\u958b"}, "threadStatus": 0, "regionId": 886, "barStatus": 0, "barId": 4, "postBy": {"utc": 1533333454000, "level": 11, "location": "\u6843\u5712\u5e02\u00b7\u53f0\u7063", "avatar": "http://filestoresg1.beetalkmobile.com:8081/file/-245435161048614809", "name": "\u7b71N"}, "id": 9187185}
