{"forum": {"content": "\u8d85\u904e30\u5c31\u4e0d\u53eb\u5b30\u5152\u80a5\u4e86<br />\u3002<br />\u3002<br />\u3002<br />\u3002<br />\u53eb\u4e2d\u5e74\u767c\u798f\u2026\u2026<br />", "images": ["http://filestoresg1.beetalkmobile.com:8081/file/40139a3167b54c029cd5c842883c3dc0", "http://filestoresg1.beetalkmobile.com:8081/file/eebbc8e295fe2bfa79725823e7e7735c"], "urls": [], "title": "\u5927\u53d4\u7248\u4e03\u5927\u4e0d\u53ef\u601d\u8b70\u4e4b\uff3f\u5973\u5927\u53d4"}, "threadStatus": 0, "regionId": 886, "barStatus": 0, "barId": 838, "postBy": {"utc": 1534651590000, "level": 8, "location": "\u65b0\u5317\u5e02\u00b7\u53f0\u7063", "avatar": "http://filestoresg1.beetalkmobile.com:8081/file/6205508410891524758", "name": "\u6211\u662f\u4f86\u6536\u96c6\u9055\u7981\u7528\u6236\u7684"}, "id": 9334102}
