{"forum": {"content": "\u611f\u60c5\u6709\u4e9b\u554f\u984c \u5f88\u7169 \u53ef\u4ee5\u8a66\u8457  \u89e3\u653e \u6559\u4f60\u8212\u58d3\u5fc3\u60c5 \u96d6\u7136\u6709\u9ede\u795e\u7d93 \u4f46\u9084\u5fd9\u8212\u670d\u9ede", "images": [], "urls": [], "title": "\u611f\u60c5\u51fa\u554f\u984c"}, "threadStatus": 0, "regionId": 886, "barStatus": 0, "barId": 13, "postBy": {"utc": 1537209847000, "level": 2, "location": "\u65b0\u5317\u5e02\u00b7\u53f0\u7063", "avatar": "http://filestoresg1.beetalkmobile.com:8081/file/8247787489795290117", "name": "skr"}, "id": 9629132}
