{"forum": {"content": "\u6211\u662f41\u6b72\u5927\u53d4\uff0c\u4f60\u6c92\u770b\u932f\uff0c\u6211\u771f\u768441\u6b72\u4e86", "images": ["http://filestoresg1.beetalkmobile.com:8081/file/e3789c7736fa1840fad134da477b5ece", "http://filestoresg1.beetalkmobile.com:8081/file/ff19900c74e058c109cb4093efc80b23", "http://filestoresg1.beetalkmobile.com:8081/file/15784b852f090cde61fd6f5d78d1e236", "http://filestoresg1.beetalkmobile.com:8081/file/24827d755d51b00f3a9a208e0857c597"], "urls": [], "title": "\u6211\u662f\u5927\u53d4"}, "threadStatus": 0, "regionId": 886, "barStatus": 0, "barId": 838, "postBy": {"utc": 1537892698000, "level": 1, "location": "\u53f0\u4e2d\u5e02\u00b7\u53f0\u7063", "avatar": "http://filestoresg1.beetalkmobile.com:8081/file/5628131762336549326", "name": "\u5f35\u5c11\u9e92"}, "id": 9709553}
