{"forum": {"content": "\u5404\u4f4d\u53ef\u4ee5\u52a0\u670b\u53cb\u4e00\u8d77\u722c\u5206\u963f", "images": ["http://filestoresg1.beetalkmobile.com:8081/file/890863f2a6f04b3b299cfaba74b6fbe3", "http://filestoresg1.beetalkmobile.com:8081/file/740e1b86c7c7b9b8b4b01751fa991eba", "http://filestoresg1.beetalkmobile.com:8081/file/55ad83cb820068be1a222e3d5add97a9"], "urls": [], "title": "\u5fb5\u6c42\u597d\u4f19\u4f34"}, "threadStatus": 0, "regionId": 886, "barStatus": 0, "barId": 60, "postBy": {"utc": 1538194350000, "level": 1, "location": "\u9ad8\u96c4\u5e02\u00b7\u53f0\u7063", "avatar": "http://filestoresg1.beetalkmobile.com:8081/file/2448757554661016680", "name": "\u912d\u5b87\u5d34"}, "id": 9744018}
