{"forum": {"content": "\u4e0d\u5962\u6c42\u4ec0\u9ebc\uff0c\u5148\u7a69\u804a\u518d\u8aaa\u5427\u22ef<br />\u5317\u90e8\u4f73", "images": ["http://filestoresg1.beetalkmobile.com:8081/file/6bedc039409951127464b3b7f15e58b1"], "urls": [], "title": "\u966a\u4f34"}, "threadStatus": 1, "regionId": 886, "barStatus": 0, "barId": 740, "postBy": {"utc": 1535636151000, "level": 1, "location": "", "avatar": "http://filestoresg1.beetalkmobile.com:8081/file/-5719582512052129280", "name": "Chen"}, "id": 9444742}
