{"forum": {"content": "\u6c92\u6709\u5f88\u53ef\u4ee5\uff0c\u4f46\u80fd\u4fdd\u8b77\u59b3<br />\u60f3\u627e\u5c0d\u8c61\u9019\u88e1\u6703\u6709\u55ce<br />\ud83d\udc67\ud83c\udffb\u5973\u5b69 \u7b49\u4f60\u4e0a\u8eca", "images": ["http://filestoresg1.beetalkmobile.com:8081/file/07e41e3ed379a785f465e551a5414bf8"], "urls": [], "title": "\ud83d\udc66\ud83c\udffb"}, "threadStatus": 0, "regionId": 886, "barStatus": 0, "barId": 20, "postBy": {"utc": 1531934232000, "level": 2, "location": "", "avatar": "http://filestoresg1.beetalkmobile.com:8081/file/6601565670856446210", "name": "+3"}, "id": 9036563}
