{"forum": {"content": "\u6709\u6c92\u6709\u4eba\u525b\u597d\u660e\u5929\u4f11\u5047\u7684\uff1f", "images": ["http://filestoresg1.beetalkmobile.com:8081/file/2efe9e08f664bef5273cf12a6db89707"], "urls": [], "title": "\u9ad8\u96c4\u9ad8\u96c4"}, "threadStatus": 0, "regionId": 886, "barStatus": 0, "barId": 20, "postBy": {"utc": 1531768387000, "level": 1, "location": "\u9ad8\u96c4\u5e02\u00b7\u53f0\u7063", "avatar": "http://filestoresg1.beetalkmobile.com:8081/file/-1748894189396325631", "name": "\u5ba5"}, "id": 9018786}
