{"forum": {"content": "\u5343\u842c\u4e0d\u8981\u8aaa\u51fa\u53bb\uff01\uff01<br />\u6211\u6559\u7df4\u771f\u7684\u5f88\u8fa3\u5c0d\u4e0d\u5c0d\uff01\uff01<br />\u9023\u540c\u5b78\u90fd\u5f88\u8fa3\u624b", "images": ["http://filestoresg1.beetalkmobile.com:8081/file/5e3b865703475bb996f68acd56fabca0", "http://filestoresg1.beetalkmobile.com:8081/file/fc2a03b8298217d1ef0fe42b580e4396", "http://filestoresg1.beetalkmobile.com:8081/file/eaa67299321a0778ba8f5f580f4965e4", "http://filestoresg1.beetalkmobile.com:8081/file/cf79fdfbb67d463c0907163e307e168f", "http://filestoresg1.beetalkmobile.com:8081/file/4f9e5d66f56d92f93f89826ec77d7e7c", "http://filestoresg1.beetalkmobile.com:8081/file/85dfdfb900ef31b5624504a5a78b2726"], "urls": [], "title": "\u5653.....\u4e0d\u8981\u8aaa\u51fa\u53bb\u311b\uff01\uff01\u6211\u662f\u7121\u804a\u5927\u5b38\u771f\u7684"}, "threadStatus": 0, "regionId": 886, "barStatus": 0, "barId": 838, "postBy": {"utc": 1536463146000, "level": 6, "location": "\u65b0\u5317\u5e02\u00b7\u53f0\u7063", "avatar": "http://filestoresg1.beetalkmobile.com:8081/file/-5127791254981914513", "name": "\uce58\uc5d4"}, "id": 9541403}
