{"forum": {"content": "<br />\u8089\u71e5\u98ef+\u55ae\u9ede\u720c\u8089\uff0c\u8089\u71e5\u98ef\u984f\u8272\u4e0d\u6df1\uff0c\u5403\u8d77\u4f86\u96d6\u7136\u53e3\u5473\u4e0d\u6fc3\uff0c\u5c6c\u65bc\u8ddf\u9ad8\u96c4\u7fd2\u6163\u7684\u5473\u9053\u4e0d\u540c\uff0c\u537b\u662f\u6703\u60f3\u518d\u5ea6\u53bb\u5403\u7684\u53e3\u5473\uff0c\u720c\u8089\u5247\u662f\u6ef7\u7684\u76ae\u8edfQ\u8089\u4e0d\u67f4\u4e7e\uff0c\u91ac\u5473\u9069\u4e2d\u3002\u5473\u564c\u6e6f\u4e5f\u8a31\u9ad8\u96c4\u4e0d\u540c\uff0c\u8abf\u5473\u4e0a\u7cd6\u6bd4\u8f03\u5c11\uff0c\u8ddf\u8089\u71e5\u98ef\u5f88\u642d\u4e0a\u7dda\u7684~~~~<br /><br />\u5f70\u5316\u720c\u8089\u98ef<br />#\u9ad8\u96c4\u5e02\u9cf3\u5c71\u5340\u81ea\u5f37\u4e8c\u8def88\u865f\u840a\u723e\u5bcc\u5c0d\u9762<br />11:00-23:00", "images": ["http://filestoresg1.beetalkmobile.com:8081/file/5e10016a18d1200b5978aed90f0c9040", "http://filestoresg1.beetalkmobile.com:8081/file/f1cd87a2c48384fe7c2c3f5ba168a086", "http://filestoresg1.beetalkmobile.com:8081/file/1c0bd261a59fd71bed39f7104403087a", "http://filestoresg1.beetalkmobile.com:8081/file/25466e4e3bf5378b36ffbeecc45d0e1d", "http://filestoresg1.beetalkmobile.com:8081/file/ca4ed00c9d04d8fa03ed695f4a88fe26", "http://filestoresg1.beetalkmobile.com:8081/file/1295545bc48070887892ce8ec6fc21e5"], "urls": [], "title": "\u597d\u5403\u7f8e\u98df"}, "threadStatus": 1, "regionId": 886, "barStatus": 0, "barId": 742, "postBy": {"utc": 1531999630000, "level": 1, "location": "\u9ad8\u96c4\u5e02\u00b7\u53f0\u7063", "avatar": "http://filestoresg1.beetalkmobile.com:8081/file/4812225962248074016", "name": "\u80d6\u5b50\ud83d\udc8b    "}, "id": 9041981}
