{"forum": {"content": "\u95dc\u7248\u524d\u5fb5\u4e00\u6ce2<br />\u65b0\u7af9\u4eba\u5728\u54ea\uff5e\uff5e\uff5e", "images": ["http://filestoresg1.beetalkmobile.com:8081/file/ef451666205f370c3744e335576a0b9b", "http://filestoresg1.beetalkmobile.com:8081/file/047575cc1ff14c95febf468e99616e5e"], "urls": [], "title": "\u8acb\u8a8d\u9818"}, "threadStatus": 0, "regionId": 886, "barStatus": 0, "barId": 205, "postBy": {"utc": 1538081598000, "level": 1, "location": "", "avatar": "http://filestoresg1.beetalkmobile.com:8081/file/-592711533026086400", "name": "Money"}, "id": 9730684}
