{"forum": {"content": "\u8acb\u554f\u81c9\u66f8\u6709\u9019\u500b\u529f\u80fd\u55ce  \u5c01\u9396\u5225\u4eba\u89e3\u9664\u6642\u7684\u6642\u9593 \u5c31\u6211\u8001\u516c\u6211\u628a\u4ed6\u5c01\u9396\u524d\u5973\u53cb\u4ed6\u53c8\u89e3\u9664\u5c31\u4e00\u76f4\u8aaa\u6211\u89e3\u9664\u7684", "images": ["http://filestoresg1.beetalkmobile.com:8081/file/a16df3c3bc743d67a95237bfc9eb0e67"], "urls": [], "title": "\u8acb\u554f"}, "threadStatus": 0, "regionId": 886, "barStatus": 0, "barId": 205, "postBy": {"utc": 1531782201000, "level": 3, "location": "\u65b0\u5317\u5e02\u00b7\u53f0\u7063", "avatar": "http://filestoresg1.beetalkmobile.com:8081/file/9018437379799874911", "name": "fish"}, "id": 9019435}
