{"forum": {"content": "\u904e\u4e86\u4e03\u5915\u7279\u5225\u5fc3\u7d2f\u2026<br />\u51fa\u9580\u88ab\u9583\ud83d\ude22\ud83d\ude22<br />\u627e\u500b\u4eba\u804a\u804a\u7d13\u89e3\u7d13\u89e3\ud83d\ude02\ud83d\ude02<br />\u55ae\u8eab\u72d7\u7684\u5fc3\u9178\u72d7\u72d7\ud83d\udc36\ud83d\udc36", "images": ["http://filestoresg1.beetalkmobile.com:8081/file/b8e0fc6affb09daa433bf4161b3620e7"], "urls": [], "title": "\u4ea4\u500b\u670b\u53cb\u804a\u804a\u5929\u5427"}, "threadStatus": 0, "regionId": 886, "barStatus": 0, "barId": 33, "postBy": {"utc": 1534600545000, "level": 1, "location": "\u53f0\u7063", "avatar": "http://filestoresg1.beetalkmobile.com:8081/file/-3933000346437343130", "name": "\u73a5\u73a5"}, "id": 9328501}
