{"forum": {"content": "\u554f \u4ec0\u9ebc\u90fd\u80fd\u554f<br /><br />\u5404\u7a2e\u7591\u96e3\u96dc\u75c7\u4e00\u4e00\u70ba\u60a8\u89e3\u7b54", "images": ["http://filestoresg1.beetalkmobile.com:8081/file/5559c950b2923bafa2164c17324365d0"], "urls": [], "title": "\u7dda\u4e0a\u554f\u4e8b\u6e2c\u5b57"}, "threadStatus": 0, "regionId": 886, "barStatus": 0, "barId": 6, "postBy": {"utc": 1537863595000, "level": 0, "location": "", "avatar": "http://filestoresg1.beetalkmobile.com:8081/file/-5319566974144555056", "name": "\u7d30\u96ea~\ud83d\ude32"}, "id": 9705520}
