{"forum": {"content": "\u4f11\u5047\u671f\u9593\u611f\u89ba\u904e\u597d\u5feb<br />\u600e\u9ebc\u4e00\u8f49\u773c\u8981\u4e0a\u73ed\u4e86\ud83d\ude02<br />\u8a72\u7e7c\u7e8c\u958b\u59cb\u52aa\u529b\u5de5\u4f5c\u4e86\u2026<br />\u6c92\u6709\u4e86\u611b\u60c5\uff0c<br />\u696d\u7e3e\u8981\u66f4\u597d\uff01<br />#\u52a0\u6cb9\u52a0\u6cb9\ud83d\udc4d<br />#\u5de5\u4f5c\u72c2\u56de\u4f86\u4e86<br />", "images": ["http://filestoresg1.beetalkmobile.com:8081/file/d2e6e3c3cbeb93b9fe00f63a6b1a8101", "http://filestoresg1.beetalkmobile.com:8081/file/96e4f9e5954d7ac1b1facfab8fcf680d"], "urls": [], "title": "\u6307\u7e2b\u5f88\u5bec\uff0c\u6642\u9593\u592a\u7626\uff0c\u6084\u6084\u5f9e\u6307\u7e2b\u9593\u6e9c\u8d70\u4e86\u2026"}, "threadStatus": 0, "regionId": 886, "barStatus": 0, "barId": 4, "postBy": {"utc": 1534395971000, "level": 5, "location": "\u65b0\u5317\u5e02\u00b7\u53f0\u7063", "avatar": "http://filestoresg1.beetalkmobile.com:8081/file/-295771911850340143", "name": "\u5929\u4f7f\u8207\u60e1\u9b54"}, "id": 9305669}
