{"forum": {"content": "\u4f86\u8a8d\u8b58\u4e9e \u59ca\u59ca\u59b9\u59b9\u90fd\u53ef\u4ee5\u5594 \u6211\u5f88\u597d\u804a\u7684", "images": ["http://filestoresg1.beetalkmobile.com:8081/file/991bd64b00962166c3babbda29e47fc7", "http://filestoresg1.beetalkmobile.com:8081/file/ace11de3346f3c2c20d5285d6884c647", "http://filestoresg1.beetalkmobile.com:8081/file/8c18dc87177e54b246e22e75f5a7fbe4"], "urls": [], "title": "\u9678\u6230\u5f1f\u5f1f\u55ae\u8eab \u91d1\u725b \u4f86\u4ea4\u670b\u53cb\u5427"}, "threadStatus": 0, "regionId": 886, "barStatus": 0, "barId": 205, "postBy": {"utc": 1533841472000, "level": 1, "location": "", "avatar": "http://filestoresg1.beetalkmobile.com:8081/file/-4656118381233571979", "name": "\u50bb\u4fde"}, "id": 9244852}
