{"forum": {"content": "\u5766\u767d\u81ea\u5df1\u61c9\u8a72\u4e0d\u662f\u4ec0\u9ebc\u96e3\u4e8b\uff0c\u90a3\u5c31\u5982\u984c\u56c9\uff0c\u4e0d\u56c9\u55e6\u4e86", "images": ["http://filestoresg1.beetalkmobile.com:8081/file/dd86246ae6fc248bd9ca85619ba24dda", "http://filestoresg1.beetalkmobile.com:8081/file/2d6c8a9d593e3912ce47e1e8b21e2f14", "http://filestoresg1.beetalkmobile.com:8081/file/a61b22f9bf86dc760425642fe1c9b972", "http://filestoresg1.beetalkmobile.com:8081/file/4599cc1913cf584788a3aabd26540fd1"], "urls": [], "title": "\u6211\u662f\u7570\u7537\uff0c\u53ef\u662f\u60f3\u8a8d\u8b58\u4e09\u6027\u7684\u5973\u5b69"}, "threadStatus": 1, "regionId": 886, "barStatus": 0, "barId": 20, "postBy": {"utc": 1535589909000, "level": 3, "location": "\u6843\u5712\u5e02\u00b7\u53f0\u7063", "avatar": "http://filestoresg1.beetalkmobile.com:8081/file/-408770933812944071", "name": "\u63b0"}, "id": 9438972}
