{"forum": {"content": "\u7121\u804a\u22ef\u22ef\u96a8\u4fbf\u5531\uff5e\uff5e\uff5e<br />\u627e\u5230\u4e00\u9996...\u570b\u5c0f\u516d\u5e74\u7d1a\u6642\u706b\u7d05\u7684\u4e00\u9996\u6b4c\ud83d\udc4d<br />\u5531\u5f97\u4e0d\u597d...\u8acb\u898b\u8ad2\u22ef\u22ef\ud83d\ude02", "images": [], "urls": [{"url": "http://17sing.tw/share_song/index.html?sid=53101567&selfUid=2009911", "thumbUrl": "http://img.17sing.tw/uc/img/head_2009911_1530903778.png", "description": "\u5927\u5bb6\u4f86\u807d\u807d\u6211\u5531\u7684\u300a\u5f8c\u4f86\u300b\n\n\u4eca\u5929\u5fc3\u60c5\u4f9d\u7136\u4e0d\u932f\uff01\n\u5531\u9996\u5976\u8336\u7684\u6b4c\uff5e\u56de\u61b6\u4e00\u4e0b\u5c0f\u5b78\u516d\u5e74\u7d1a\ud83d\ude02\n\u56e0\u70ba\u9019\u9996\u6b4c\u662f\u5728\u90a3\u500b\u6642\u5019\u51fa\u4f86\u7684\ud83d\ude02\ud83d\ude02\ud83d\ude02\n\u5531\u5f97\u4e0d\u597d\uff0c\u8acb\u5305\u542b\u311a\u22ef\u22ef\ud83d\ude07\ud83d\ude07\ud83d\ude07", "title": "\u6b61\u6b4c\u5206\u4eab"}], "title": "\u7df4\u55d3\u5b50"}, "threadStatus": 0, "regionId": 886, "barStatus": 0, "barId": 850, "postBy": {"utc": 1536332019000, "level": 3, "location": "", "avatar": "http://filestoresg1.beetalkmobile.com:8081/file/-206661981197931003", "name": "\u60d7\u60e0"}, "id": 9527197}
