{"forum": {"content": "\u653e\u5047\u771f\u7684\u653e\u5230\u5f88\u7121\u804a\u54c8\u54c8", "images": ["http://filestoresg1.beetalkmobile.com:8081/file/8e8a58fa10617f2dc38c9c1b9df4da97"], "urls": [], "title": "\u804a\u5929"}, "threadStatus": 0, "regionId": 886, "barStatus": 0, "barId": 205, "postBy": {"utc": 1536225287000, "level": 1, "location": "\u9ad8\u96c4\u5e02\u00b7\u53f0\u7063", "avatar": "http://filestoresg1.beetalkmobile.com:8081/file/4369863854713173858", "name": "\u767d\u767d\u2763\ufe0f"}, "id": 9513184}
