{"forum": {"content": "70\u5e74\u4ee3\u51fa\u751f\uff0c\u6709\u4e00\u4efd\u7a69\u5b9a\u7684\u5de5\u4f5c\uff0c\u6709\u4e00\u9593\u6b63\u5728\u7e73\u6b3e\u7684\u623f\u5b50\uff0c\u6709\u4e00\u53f0\u4e0d\u7528\u64d4\u5fc3\u5b89\u5fc3\u6dcb\u96e8\u53ef\u4ee3\u6b65\u8eca\u3002\u5e0c\u671b\u6709\u7de3\u7684\u59b3\u53ef\u4ee5\u8ddf\u6211\u4e00\u8d77\u65c5\u884c\u4e00\u8d77\u4eab\u53d7\u559c\u6012\u54c0\u6a02", "images": ["http://filestoresg1.beetalkmobile.com:8081/file/b77ceb6252d15903e395e58106731ce0", "http://filestoresg1.beetalkmobile.com:8081/file/09140337161ac5ff2b5994344de52ee4", "http://filestoresg1.beetalkmobile.com:8081/file/8c1cd3c476ac443c3d80eabb9181ba0c"], "urls": [], "title": "\u60f3\u627e\u4e00\u500b\u7a69\u5b9a\u7684\u5c0d\u8c61\u7d50\u5a5a"}, "threadStatus": 0, "regionId": 886, "barStatus": 0, "barId": 740, "postBy": {"utc": 1536285727000, "level": 3, "location": "\u57fa\u9686\u5e02\u00b7\u53f0\u7063", "avatar": "http://filestoresg1.beetalkmobile.com:8081/file/-6222888366573115645", "name": "Peter.C"}, "id": 9520823}
