{"forum": {"content": "\u6bcf\u9031\u4e09\u90fd\u6703\u8dd1\u7d05\u78da\u559d\u9152 \u5c0b\u6c42\u9152\u4f34", "images": ["http://filestoresg1.beetalkmobile.com:8081/file/3d1b46f7d652925d32f480c2c70ee763", "http://filestoresg1.beetalkmobile.com:8081/file/3b26e8b43d78dade6f6a367f17a4360c", "http://filestoresg1.beetalkmobile.com:8081/file/b424472668f4f77a3d055461cf899dbf"], "urls": [], "title": "\u6709\u4eba\u8981\u4e00\u8d77\u9ad8\u96c4\u7d05\u78da\u5730\u7a96\u55ce\uff1f"}, "threadStatus": 0, "regionId": 886, "barStatus": 0, "barId": 792, "postBy": {"utc": 1534833171000, "level": 1, "location": "\u9ad8\u96c4\u5e02\u00b7\u53f0\u7063", "avatar": "http://filestoresg1.beetalkmobile.com:8081/file/201434929219666208", "name": "FB:\u9b4f\u7b71\u4f73"}, "id": 9355409}
