{"forum": {"content": "Do you want to be a special person?\ud83d\ude01\ud83d\ude01\ud83d\ude01", "images": ["http://filestoresg1.beetalkmobile.com:8081/file/e2b9008f32e26f22b50df6d8c5cffbd6"], "urls": [], "title": "\u7d66\u8a8d\u8b58\u4e00\u4e0b\u55ce\uff1f"}, "threadStatus": 0, "regionId": 886, "barStatus": 0, "barId": 205, "postBy": {"utc": 1538309618000, "level": 1, "location": "\u53f0\u7063", "avatar": "http://filestoresg1.beetalkmobile.com:8081/file/-1994035799724178107", "name": "\u96f6"}, "id": 9762323}
