{"forum": {"content": "\u7e3d\u89ba\u5f97\u81ea\u5df1\u6c92\u4ec0\u9ebc\u7570\u6027\u7de3....", "images": ["http://filestoresg1.beetalkmobile.com:8081/file/d76582bf25480294a3ed29f5e6b7f7dc"], "urls": [], "title": "\u6211\u4e5f\u60f3\u8981\u6709\u500b\u4f34\ud83d\ude2d"}, "threadStatus": 1, "regionId": 886, "barStatus": 0, "barId": 740, "postBy": {"utc": 1533049801000, "level": 3, "location": "", "avatar": "http://filestoresg1.beetalkmobile.com:8081/file/4846385572770438415", "name": "\u6b50\u5df4\ud83d\udc53"}, "id": 9157168}
