{"forum": {"content": "\u9019\u4e16\u754c\u5f88\u516c\u5e73<br /><br />\u60f3\u8981\u6700\u597d<br /><br />\u5c31\u4e00\u5b9a\u6703\u7d66\u6700\u75db<br /><br />\u80fd\u95d6\u904e\u53bb<br /><br />\u5c31\u662f\u8d0f\u5bb6<br /><br />\u95d6\u4e0d\u904e\u53bb<br /><br />\u90a3\u5c31\u4e56\u4e56\u505a\u666e\u901a\u4eba<br /><br />\u6240\u8b02\u6210\u529f<br /><br />\u4e26\u4e0d\u662f\u770b\u6709\u591a\u8070\u660e<br /><br />\u4e5f\u4e0d\u662f\u51fa\u8ce3\u81ea\u5df1<br /><br />\u800c\u662f\u770b\u80fd\u5426\u7b11\u8457\u6e21\u904e\u96e3\u95dc", "images": ["http://filestoresg1.beetalkmobile.com:8081/file/bca16d8355ed75ad0bbef035293dc4bc"], "urls": [], "title": "\u96a8\u60f33"}, "threadStatus": 0, "regionId": 886, "barStatus": 0, "barId": 707, "postBy": {"utc": 1535902086000, "level": 15, "location": "\u6843\u5712\u5e02\u00b7\u53f0\u7063", "avatar": "http://filestoresg1.beetalkmobile.com:8081/file/-2490333345820353303", "name": "sam\u627f\u667a"}, "id": 9475406}
