{"forum": {"content": "\u73fe\u5728\u8a50\u9a19\u96c6\u5718\u5c64\u51fa\u4e0d\u7aae<br />\u9084\u80fd\u7528\u7db2\u8def\u653b\u64ca\u65b9\u5f0f\u7372\u5229\uff1f<br />\u70ba\u4f55\u53ea\u8981\u653b\u64ca\u5a1b\u6a02\u57ce\uff1f<br />\u5e79\u561b\u4e0d\u53bb\u653b\u64ca\u570b\u5167\u77e5\u540d\u91d1\u63a7\uff1f<br />\u90a3\u4e0d\u662f\u8cfa\u66f4\u591a\u55ce.....<br /><br />\u5225\u88ab\u8a50\u9a19\u4e86....\u505a\u5922\uff01\uff01", "images": ["http://filestoresg1.beetalkmobile.com:8081/file/82a7cef2e248a36819fa90feddfafa8a", "http://filestoresg1.beetalkmobile.com:8081/file/2cefba8e7d14cefc578de3e41a05f693", "http://filestoresg1.beetalkmobile.com:8081/file/65b67af096310ffea0d88b39cdb02b86", "http://filestoresg1.beetalkmobile.com:8081/file/ae73708c3bca0f65e5b611ebcb91606c", "http://filestoresg1.beetalkmobile.com:8081/file/36c9d212f21b279e71744474cffccb8b", "http://filestoresg1.beetalkmobile.com:8081/file/fe1ad7a2c599f6a0564c23d6935ce6c0"], "urls": [], "title": "\u505a\u5922"}, "threadStatus": 0, "regionId": 886, "barStatus": 0, "barId": 758, "postBy": {"utc": 1538055430000, "level": 0, "location": "\u53f0\u4e2d\u5e02\u00b7\u53f0\u7063", "avatar": "http://filestoresg1.beetalkmobile.com:8081/file/-779478961654764261", "name": "\u7dad"}, "id": 9727417}
