{"forum": {"content": "\u4e0a\u5b63\u5c0f\u767d\u91d1 \u76ee\u524d\u5c0f\u5c0f\u91d1\u6709\u4eba\u8981\u4e00\u8d77\u722c\u5206\u55ce", "images": ["http://filestoresg1.beetalkmobile.com:8081/file/0feb0f43c104f9dfd1c295b706a0d0a4"], "urls": [], "title": "\u5fb5sup\u4e00\u8d77\u722c\u5206"}, "threadStatus": 0, "regionId": 886, "barStatus": 0, "barId": 60, "postBy": {"utc": 1534772304000, "level": 1, "location": "", "avatar": "http://filestoresg1.beetalkmobile.com:8081/file/-3823504403098847743", "name": "\u4ec1"}, "id": 9348762}
