{"forum": {"content": "\u6709\u4eba\u5728\u73a9IG\u7684\u55ce\uff1f\u4f86\u8ffd\u8e64\u311a\uff5e\u804a\u5929\u804a\u5929<br />siao_lin_0622", "images": ["http://filestoresg1.beetalkmobile.com:8081/file/cb1a187600cb1206cd6bb8ffae676967"], "urls": [], "title": "\u525b\u6eff16y\u6c92\u591a\u4e45\u7684\u8001\u9ad8\u4e8c\u751f"}, "threadStatus": 1, "regionId": 886, "barStatus": 0, "barId": 438, "postBy": {"utc": 1535714372000, "level": 3, "location": "", "avatar": "http://filestoresg1.beetalkmobile.com:8081/file/6243727434139199748", "name": "\u5b8b."}, "id": 9453005}
