{"forum": {"content": "\u597d\u60f3\u812b\u96e2\u55ae\u8eab \u597d\u597d\u611b\u4e00\u500b\u4eba \u4e00\u8d77\u75db\u54ed \u4e00\u8d77\u7b11 \u4e00\u8d77\u651c\u624b\u6253\u62fc", "images": ["http://filestoresg1.beetalkmobile.com:8081/file/9bb67aa13af48654ee2e455ecad69220"], "urls": [], "title": "\u5fb5\u5fb5\u5fb5"}, "threadStatus": 0, "regionId": 886, "barStatus": 0, "barId": 766, "postBy": {"utc": 1537808228000, "level": 0, "location": "", "avatar": "http://filestoresg1.beetalkmobile.com:8081/file/-2203505942104011005", "name": "\u85cd\u8272\u6d77\u6d0b"}, "id": 9700089}
