{"forum": {"content": "\u919c\u5973\u6709\u4eba\u8981\u8a8d\u8b58\u55ce\u0ca5_\u0ca5", "images": ["http://filestoresg1.beetalkmobile.com:8081/file/e6dd4ef9c437e7bcdc13a5700fbdc996"], "urls": [], "title": "\u5fb5\u500b\u670b\u53cb\u5504\u2764\ufe0f"}, "threadStatus": 0, "regionId": 886, "barStatus": 0, "barId": 205, "postBy": {"utc": 1535802028000, "level": 3, "location": "\u65b0\u7af9\u5e02\u00b7\u53f0\u7063", "avatar": "http://filestoresg1.beetalkmobile.com:8081/file/2799538043227310855", "name": "159\u59b9\u5b50\u2764\ufe0f"}, "id": 9462591}
