{"forum": {"content": "\u6bcf\u6b21\u90fd\u6703\u60f3\u6771\u60f3\u897f\u4e82\u4e03\u516b\u7cdf\u53c8\u88dd\u93ae\u5b9a\ud83d\ude02\u4f60\u5011\u77e5\u9053\u55ce\ud83d\ude02", "images": ["http://filestoresg1.beetalkmobile.com:8081/file/3a69ed9b0ab80dc00a6f719c9cb712ab"], "urls": [], "title": "\u5de8\u87f9\u5ea7"}, "threadStatus": 1, "regionId": 886, "barStatus": 0, "barId": 33, "postBy": {"utc": 1536849060000, "level": 0, "location": "\u6843\u5712\u5e02\u00b7\u53f0\u7063", "avatar": "http://filestoresg1.beetalkmobile.com:8081/file/-1964530393773612706", "name": "Joe"}, "id": 9587839}
