{"forum": {"content": "\u5509\u5537~\u7ba1\u7406\u54e1\u5927\u5927\u9019\u9ebc\u5b98\u50da\u554a\uff1f<br />\u5973\u751f\u8cbc\u6e23\u7537\u7684\u6587\u7ae0\u5c31\u6c92\u4e8b\uff0c<br />\u7537\u751f\u8cbc\u6e23\u5973\u7684\u6587\u7ae0\u5c31\u88ab\u522a\uff1f<br /><br />\u5616\u5616~\u5b98\u4e0d\u5927\uff0c\u50da\u6c23\u5012\u4e0d\u5c0f\u554a\uff01<br />\u4f69\u670d~\u4f69\u670d~", "images": ["http://filestoresg1.beetalkmobile.com:8081/file/638ddcac1d6761b88ac2559af9b1bfca"], "urls": [], "title": "\u5475\u5475~\u73fe\u5728\u662f\u6027\u5225\u6b67\u8996\u4e86\uff1f"}, "threadStatus": 0, "regionId": 886, "barStatus": 0, "barId": 391, "postBy": {"utc": 1532761495000, "level": 0, "location": "", "avatar": "http://filestoresg1.beetalkmobile.com:8081/file/2", "name": "User blocked"}, "id": 9123922}
