{"forum": {"content": "\u9019\u6a23\u53ef\u4ee5\u55ce\u54c8\u54c8", "images": ["http://filestoresg1.beetalkmobile.com:8081/file/1fd1d5f0c73b34b7d7c483569a5593b8"], "urls": [], "title": "\u60f3\u8a8d\u8b58\u59ca\u59ca"}, "threadStatus": 0, "regionId": 886, "barStatus": 0, "barId": 734, "postBy": {"utc": 1532046887000, "level": 3, "location": "\u53f0\u5317\u5e02\u00b7\u53f0\u7063", "avatar": "http://filestoresg1.beetalkmobile.com:8081/file/5214764867267782661", "name": "DeadBoy Trippy."}, "id": 9047017}
