{"forum": {"content": "\u4e0d\u77e5\u9053\u6d77\u5de1\u7f72\u53ef\u4e0d\u53ef\u4ee5\u4e82\u5165\ud83d\ude02\ud83d\ude02", "images": ["http://filestoresg1.beetalkmobile.com:8081/file/247ae4a790cacfe0e35d498d5f3a7d7d"], "urls": [], "title": "\u57f7\u6cd5\u55ae\u4f4d"}, "threadStatus": 0, "regionId": 886, "barStatus": 0, "barId": 704, "postBy": {"utc": 1536181757000, "level": 1, "location": "\u6f8e\u6e56\u7e23\u00b7\u53f0\u7063", "avatar": "http://filestoresg1.beetalkmobile.com:8081/file/-7830218230474355193", "name": "   Twrn"}, "id": 9508659}
