{"forum": {"content": "\u53c8\u591a\u4f54\u4e86\u597d\u5e7e\u500b\u5730\u76e4\u3002", "images": ["http://filestoresg1.beetalkmobile.com:8081/file/33b4c76eb534829f53b91302a16e3479", "http://filestoresg1.beetalkmobile.com:8081/file/f4107c0112cd3cd6009758d84220ac63", "http://filestoresg1.beetalkmobile.com:8081/file/9a4ae0515ea251c0c656ae0d9f4b194b", "http://filestoresg1.beetalkmobile.com:8081/file/e9820225ed8631662b5e5028d78507b0", "http://filestoresg1.beetalkmobile.com:8081/file/a34393427c998db0d2242ee97a9a113f", "http://filestoresg1.beetalkmobile.com:8081/file/58d285f08f559ba73624b651e2bb0f4f"], "urls": [], "title": "\u6c92\u73a9\u5230\u71b1\u6c23\u7403~\u6b98\u5ff5\u2026\u2026"}, "threadStatus": 0, "regionId": 886, "barStatus": 0, "barId": 750, "postBy": {"utc": 1532275656000, "level": 3, "location": "\u53f0\u7063", "avatar": "http://filestoresg1.beetalkmobile.com:8081/file/2403679754169965824", "name": "00000"}, "id": 9072529}
