{"forum": {"content": "\u6b64\u4eba\u5c0f\u5fc3\uff01<br />\u76dc\u4eba\u7167\u7247\u9084\u53ef\u4ee5\u90a3\u9ebc\u56c2\u5f35\uff1f<br />\u4f60\u6709\u6c92\u6709\u7f9e\u6065\u5fc3\uff1f<br />\u8acb\u5927\u5bb6\u5e6b\u500b\u5fd9\u6295\u8a34\u4ed6<br />\u5982\u679c\u4f60\u5011\u6709\u9047\u5230\u4ed6\u53ef\u4ee5\u4e0d\u8981\u7406\u4ed6<br />\u4ed6\u6839\u672c\u53ea\u662f\u4f86\u9a19\u70ae\u7684\uff01<br />\u5927\u5bb6\u5c0f\u5fc3\u4e0d\u8981\u88ab\u4ed6\u9a19\u4e86\uff01", "images": ["http://filestoresg1.beetalkmobile.com:8081/file/8acc3e1c342f7fffde76966903a11058"], "urls": [], "title": "\u6b64\u4eba\u5c0f\u5fc3"}, "threadStatus": 0, "regionId": 886, "barStatus": 0, "barId": 20, "postBy": {"utc": 1538285244000, "level": 4, "location": "\u9ad8\u96c4\u5e02\u00b7\u53f0\u7063", "avatar": "http://filestoresg1.beetalkmobile.com:8081/file/6264533494579732104", "name": "\u5c0f\u6069"}, "id": 9757878}
