{"forum": {"content": "\u6843\u5712\u6a19\u6e96\u591c\u8c93\uff5e\uff5e<br />\u6c42\u804a\u5929\ud83e\udd23\u534a\u591c\u5f88\u7121\u804a\u5167<br />\u6c42\u5e36\u8d70\ud83e\udd23\ud83e\udd23", "images": ["http://filestoresg1.beetalkmobile.com:8081/file/e551eef211f9d46a096d4daec8e016c3"], "urls": [], "title": "\u6a19\u6e96\u591c\u8c93\u6c42\u8a8d\u8b58"}, "threadStatus": 0, "regionId": 886, "barStatus": 0, "barId": 20, "postBy": {"utc": 1535211629000, "level": 2, "location": "\u6843\u5712\u5e02\u00b7\u53f0\u7063", "avatar": "http://filestoresg1.beetalkmobile.com:8081/file/728881674503844096", "name": "\u6ab8\u6aac"}, "id": 9396752}
