{"forum": {"content": "\u966a\u4f60\u02cb\u5f9e0\u5230\u73fe\u5728\u4f60\u958b\u516c\u53f8\u4f60\u7576\u5175\u4e5f\u7b49<br />\u4e94\u5e74\u611f\u60c5\u4f60\u8ddf\u6211\u8aaa\u4f60\u4e0d\u96e3\u904e\u6c92\u6709\u54ed\u904e<br />\u90a3\u6211\u70ba\u4f60\u9019\u500b\u7537\u4eba\u4e00\u76f4\u54ed\uff0c\u6211\u60f3\u5feb\u9ede\u8d70\u51fa\u4f86<br />", "images": ["http://filestoresg1.beetalkmobile.com:8081/file/04432b1643f0798bcfd9615a955f656b", "http://filestoresg1.beetalkmobile.com:8081/file/b81e7c2cac0552d6019c8c3afeddc7e6"], "urls": [], "title": "\u4ea4\u5f80\u4e94\u5e74\u88ab\u7529"}, "threadStatus": 0, "regionId": 886, "barStatus": 0, "barId": 205, "postBy": {"utc": 1537821153000, "level": 1, "location": "", "avatar": "http://filestoresg1.beetalkmobile.com:8081/file/-7395000722316547177", "name": "\u857e\u9708"}, "id": 9701252}
