{"forum": {"content": "\u60f3\u5b78\u5316\u599d\u6253\u626e \u5b78\u7fd2\u9069\u5408\u81ea\u5df1\u7684\u599d\u5bb9\u548c\u5316\u599d\u7684\u7f8e\u5b78 \u6709\u4eba\u9858\u610f\u6559\u6559\u5c0f\u59b9\u6211\u55ce\ud83e\udd15\ud83e\udd15", "images": ["http://filestoresg1.beetalkmobile.com:8081/file/35269b631034ed49fc43fff3c5bea7bb"], "urls": [], "title": "\u60f3\u5b78\u5316\u599d\u6253\u626e(\uff61\u2022\u0301\ufe3f\u2022\u0300\uff61)"}, "threadStatus": 0, "regionId": 886, "barStatus": 0, "barId": 706, "postBy": {"utc": 1531734421000, "level": 1, "location": "\u53f0\u7063", "avatar": "http://filestoresg1.beetalkmobile.com:8081/file/-4558045242826251785", "name": "\u591c\u96ea"}, "id": 9014165}
