{"forum": {"content": "\u54c8\u3002\u3002\u807d\u807d\u770b\u5427\uff01", "images": [], "urls": [{"url": "http://17sing.tw/share_song/index.html?sid=40713610", "thumbUrl": "http://img.17sing.tw/uc/img/head_3614325_1532530866.png", "description": "\u5927\u5bb6\u4f86\u807d\u807d\u6211\u5531\u7684 \u300a\u96b1\u5f62\u7684\u7fc5\u8180\u300b", "title": "\u6b61\u6b4c\u5206\u4eab"}], "title": "\u96b1\u5f62\u7684\u7fc5\u8180"}, "threadStatus": 1, "regionId": 886, "barStatus": 0, "barId": 850, "postBy": {"utc": 1537413997000, "level": 1, "location": "\u9ad8\u96c4\u5e02\u00b7\u53f0\u7063", "avatar": "http://filestoresg1.beetalkmobile.com:8081/file/-8469646919143555213", "name": "\u84c1\u701e"}, "id": 9651217}
