{"forum": {"content": "\u627e\u5230\u7b2c\u4e8c\u4efd\u5de5\u4f5c\u560d\u2764\u2764<br />\u958b\u5fc3\u958b\u5fc3\ud83d\udc8b\ud83d\udc8b<br />\u6211\u8981\u52aa\u529b\u5b58\u9322\uff0c\u8001\u4e86\uff01\u624d\u4e0d\u7528\u6015\u6c92\u4eba\u990a\u6211", "images": ["http://filestoresg1.beetalkmobile.com:8081/file/725b294c35c4aa05d47232eef20a1ac5"], "urls": [], "title": "\u54c8\u54c8\uff01\u559c\u6b61\u81ea\u62cd\u2764"}, "threadStatus": 0, "regionId": 886, "barStatus": 0, "barId": 4, "postBy": {"utc": 1537375537000, "level": 2, "location": "", "avatar": "http://filestoresg1.beetalkmobile.com:8081/file/7641829036661702470", "name": "\ud83d\udc8b\u80a5\u5b85\u5154\ud83d\udc8b"}, "id": 9648099}
