{"forum": {"content": "\u6bcf\u5929\u5fd9\u788c\u7684\u5de5\u4f5c\uff0c\u597d\u7d2f\u5537", "images": ["http://filestoresg1.beetalkmobile.com:8081/file/59f834cbebf8ec59b3cdeb4c0b87f90e"], "urls": [], "title": "30\u4e86\u597d\u5feb\u5feb\u8b8a\u5927\u53d4\u4e86"}, "threadStatus": 0, "regionId": 886, "barStatus": 0, "barId": 838, "postBy": {"utc": 1534165433000, "level": 3, "location": "\u6843\u5712\u5e02\u00b7\u53f0\u7063", "avatar": "http://filestoresg1.beetalkmobile.com:8081/file/3806534545629653519", "name": "\u9aee\u578b\u5e2b"}, "id": 9280904}
