{"forum": {"content": "\u4f60\u6d3b\u8457\u7684\u6642\u5019\u61c9\u4ed8\u4e0d\u4e86\u751f\u6d3b\uff0c\u5c31\u61c9\u8a72\u7528\u4e00\u96bb\u624b\u64cb\u958b\u9ede\u7c60\u7f69\u8457\u4f60\u7684\u547d\u904b\u7684\u7d55\u671b\uff0c\u540c\u6642\uff0c\u7528\u53e6\u4e00\u96bb\u624b\u8a18\u4e0b\u4f60\u5728\u5ee2\u589f\u4e2d\u770b\u5230\u7684\u4e00\u5207\u3002", "images": ["http://filestoresg1.beetalkmobile.com:8081/file/10ce03731fd1299d11b35f0666ce2adf"], "urls": [], "title": ""}, "threadStatus": 0, "regionId": 886, "barStatus": 0, "barId": 707, "postBy": {"utc": 1537355013000, "level": 16, "location": "", "avatar": "http://filestoresg1.beetalkmobile.com:8081/file/-6138018139888995295", "name": "\u6d41\u6d6a\u8c93\uff08\u8b8a\u58de\u7684\u597d\u4eba\uff09"}, "id": 9644533}
