{"forum": {"content": "\u6211\u767c\u73fe\u9019\u7248\u3001\u6b63\u5e38\u4eba\u771f\u5c11\u767c\u8a00", "images": ["http://filestoresg1.beetalkmobile.com:8081/file/559382526e8f1779841d69fb8dc655c1"], "urls": [], "title": "\u6ca1\u6709\u4e00\u500b\u662f\u6b63\u5e38\u7684"}, "threadStatus": 0, "regionId": 886, "barStatus": 0, "barId": 838, "postBy": {"utc": 1532155787000, "level": 8, "location": "\u53f0\u7063", "avatar": "http://filestoresg1.beetalkmobile.com:8081/file/3839674931836654002", "name": "\u963f\u5169"}, "id": 9058449}
