{"forum": {"content": "\u7531\u65bc\u6c92\u670b\u53cb\u4e00\u8d77\u73a9\uff0c\u6240\u4ee5\u770b\u6709\u7121\u540c\u597d\u56c9\uff0c\u8b1d\u8b1d", "images": ["http://filestoresg1.beetalkmobile.com:8081/file/9213b062426176e4789fe1657ccdb5b5"], "urls": [], "title": "\u8aa0\u5fb5\u5bf6\u53cb\u5927\u53f0\u5317\u5730\u5340\uff08\u6bcf\u65e5\u9001\u79ae\u5594\uff09\uff01\uff01"}, "threadStatus": 0, "regionId": 886, "barStatus": 0, "barId": 820, "postBy": {"utc": 1532158276000, "level": 2, "location": "\u65b0\u5317\u5e02\u00b7\u53f0\u7063", "avatar": "http://filestoresg1.beetalkmobile.com:8081/file/-59544038395243027", "name": "\u4e39\u5c3c\u65af"}, "id": 9058718}
