{"forum": {"content": "\u5c31\u7d04\u62cd\u9760\u7de3\u4efd", "images": ["http://filestoresg1.beetalkmobile.com:8081/file/65c64116b83b657e5e7780a6dc4432f8", "http://filestoresg1.beetalkmobile.com:8081/file/541c15860e176b06bd70abaa28419b67", "http://filestoresg1.beetalkmobile.com:8081/file/2fade0836fce4b77e92eae40ca5bf321", "http://filestoresg1.beetalkmobile.com:8081/file/cb0c6df0fa5093f3bdfb3bd13a7fc111", "http://filestoresg1.beetalkmobile.com:8081/file/ea887c9877b41d07e1644f2668502c9e", "http://filestoresg1.beetalkmobile.com:8081/file/85796952713118f2379638f83501da1a"], "urls": [], "title": "\u65c5\u62cd\u5206\u4eab"}, "threadStatus": 1, "regionId": 886, "barStatus": 0, "barId": 77, "postBy": {"utc": 1537876450000, "level": 23, "location": "", "avatar": "http://filestoresg1.beetalkmobile.com:8081/file/-5618351584950110976", "name": "\u6211\u53ea\u662f\u4e00\u584a\u96ea\u82b1\u725b"}, "id": 9706915}
