{"forum": {"content": "\u6211\u4e5f\u5e0c\u671b\u81ea\u5df1\u662f\u500b\u5c0f\u5973\u5b69<br />\u5973\u4eba\u5fc3 \ud83d\udc8c\ud83d\udc8c", "images": ["http://filestoresg1.beetalkmobile.com:8081/file/261fff2b251302fd69d837e93d63aeb8"], "urls": [], "title": "\u5f70\u5316\u4eba \u7279\u5225\u55c6"}, "threadStatus": 0, "regionId": 886, "barStatus": 0, "barId": 674, "postBy": {"utc": 1531856910000, "level": 1, "location": "\u53f0\u7063", "avatar": "http://filestoresg1.beetalkmobile.com:8081/file/2", "name": "User blocked"}, "id": 9028374}
