{"forum": {"content": "\u6709\u6642\u5019\u9078\u64c7\u6703\u9020\u5c31\u5f88\u591a\u4e8b<br />\u6642\u52e2\u9020\u82f1\u96c4<br />\u6642\u6a5f\u4f86\u4e86\u4e00\u8d77\u5f80\u524d\u885d<br />\u5982\u679c\u4f60\u6709\u4e00\u9846\u5f88\u62fc\u7684\u5fc3<br />\u4e0d\u6015\u82e6\u4e0d\u6015\u7d2f<br />\u6b61\u8fce\u4f86\u627e\u6211<br />\u8b93\u6211\u5011\u4e00\u8d77\u8b8a\u5f97\u66f4\u5f37<br />\u8b93\u6211\u5011\u53ef\u4ee5\u6539\u8b8a\u4e16\u754c", "images": ["http://filestoresg1.beetalkmobile.com:8081/file/c7962c5128b3433b79ba2c17fb0a7fb2", "http://filestoresg1.beetalkmobile.com:8081/file/11bccc370cce3698441c6d50f0af7d79"], "urls": [], "title": "\u6642\u52e2\u9020\u82f1\u96c4"}, "threadStatus": 1, "regionId": 886, "barStatus": 0, "barId": 205, "postBy": {"utc": 1532970088000, "level": 1, "location": "", "avatar": "http://filestoresg1.beetalkmobile.com:8081/file/5697092035213785345", "name": "We"}, "id": 9149139}
