{"forum": {"content": "\u58de\uff1a\u9577\u5b98\u7121\u8166<br />\u597d\uff1a\u8a8d\u8b58\u4e86\u4f60\u5011\uff01\uff01\uff01", "images": ["http://filestoresg1.beetalkmobile.com:8081/file/a1adf19e5a3420eea99703d2cf83e7d7"], "urls": [], "title": "\u7576\u5175\u58de\u8207\u597d"}, "threadStatus": 0, "regionId": 886, "barStatus": 0, "barId": 704, "postBy": {"utc": 1537460026000, "level": 2, "location": "", "avatar": "http://filestoresg1.beetalkmobile.com:8081/file/-6800511280100186624", "name": "\u5468\u5927\u80c3"}, "id": 9657555}
