{"forum": {"content": "\u5230\u8655\u947d\u5230\u8655\u90fd\u80fd\u7761\uff0c\u6211\u5011\u5bb6\u7684\u8c93\u723a\uff0c\u8d95\u4ed6\u9084\u751f\u6c23\u8981\u54ac\u4eba\u5462\uff5e\ud83d\ude02", "images": ["http://filestoresg1.beetalkmobile.com:8081/file/92b3d7a5bd229d6c01a5bfec5288f59e", "http://filestoresg1.beetalkmobile.com:8081/file/aba84e1cf0dd3ca53972c4ae2e413059", "http://filestoresg1.beetalkmobile.com:8081/file/d38cbddd70734dc7ac7e3a5e3c9a62cf", "http://filestoresg1.beetalkmobile.com:8081/file/324ec2ac562b53cb4b6e141b3be9a610", "http://filestoresg1.beetalkmobile.com:8081/file/761af39858bec853c34bf74513e957fe", "http://filestoresg1.beetalkmobile.com:8081/file/51d504e41f49b7c9d0e359687a9f9561"], "urls": [], "title": "\u5230\u8655\u90fd\u662f\u4ed6\u5730\u76e4"}, "threadStatus": 0, "regionId": 886, "barStatus": 0, "barId": 751, "postBy": {"utc": 1536999157000, "level": 3, "location": "\u9ad8\u96c4\u5e02\u00b7\u53f0\u7063", "avatar": "http://filestoresg1.beetalkmobile.com:8081/file/-944130820172831212", "name": "\u674e\u5c0f\u771f"}, "id": 9603571}
