{"forum": {"content": "1977\u53f0\u4e2d<br />\u4ea4\u670b\u53cb<br />\u540c\u5b78\u5011\u4e00\u8d77\u804a", "images": ["http://filestoresg1.beetalkmobile.com:8081/file/61342302872d849bedd551ce155b3653", "http://filestoresg1.beetalkmobile.com:8081/file/626f992a9db2489f54c585e573ee2c46"], "urls": [], "title": "1977\u53f0\u4e2d"}, "threadStatus": 0, "regionId": 886, "barStatus": 0, "barId": 746, "postBy": {"utc": 1536017810000, "level": 2, "location": "\u53f0\u4e2d\u5e02\u00b7\u53f0\u7063", "avatar": "http://filestoresg1.beetalkmobile.com:8081/file/-4651146384499147234", "name": "\u91d1\u5361\u7d0d"}, "id": 9488221}
