{"forum": {"content": "\u5230\u5e95\u70ba\u4ec0\u9ebc\u5927\u5bb6\u770b\u5230\u8d99\u96f2\u90fd\u5404\u7a2e\u903c\u63db\u89d2\u8272\uff1f<br />\u660e\u660e\u5f88\u5147\u554a", "images": ["http://filestoresg1.beetalkmobile.com:8081/file/08cc9abb03ddec82b9552b0087e6ff46", "http://filestoresg1.beetalkmobile.com:8081/file/e926015689dc6ddaa2965d8cf1c32586", "http://filestoresg1.beetalkmobile.com:8081/file/fb4c5c15c325187cce052b100dede92a", "http://filestoresg1.beetalkmobile.com:8081/file/36013cd167f05ff30d1c65f429853324"], "urls": [], "title": "\u7b2c\u4e00\u6b21\u9019\u9ebc\u5147"}, "threadStatus": 0, "regionId": 886, "barStatus": 0, "barId": 841, "postBy": {"utc": 1534761417000, "level": 6, "location": "\u9ad8\u96c4\u5e02\u00b7\u53f0\u7063", "avatar": "http://filestoresg1.beetalkmobile.com:8081/file/3699105663369694726", "name": "\u591c"}, "id": 9346987}
