{"forum": {"content": "\u96f2\u9727\u9b54\u6cd5\u5e2b<br /><br />#Taiwan #Taipei #NewTaipeiCity #\u9060\u65b9 #\u65e5\u5e38 #\u5927\u6a4b\u98a8\u666f", "images": ["http://filestoresg1.beetalkmobile.com:8081/file/6e3ebb55f283a8bef8de5f71f7854c26", "http://filestoresg1.beetalkmobile.com:8081/file/c13f278239cea57bf1e788b8f9fd27be", "http://filestoresg1.beetalkmobile.com:8081/file/bb7d033f0fde3d0f8f0791e00d000ce6", "http://filestoresg1.beetalkmobile.com:8081/file/05eee3af30867d2b8a953e830767533e"], "urls": [], "title": "\u5927\u6a4b\u98a8\u666f-\u83ef\u6c5f\u6a4b"}, "threadStatus": 0, "regionId": 886, "barStatus": 0, "barId": 77, "postBy": {"utc": 1532338970000, "level": 18, "location": "\u53f0\u5317\u5e02\u00b7\u53f0\u7063", "avatar": "http://filestoresg1.beetalkmobile.com:8081/file/6460007956778640527", "name": "\u674e\u632f\u767c"}, "id": 9078376}
