{"forum": {"content": "\u5728\u96f2\u6797\u9109\u4e0b\u597d\u7121\u804a", "images": ["http://filestoresg1.beetalkmobile.com:8081/file/69c966a078958bb55762fe053c484ac1", "http://filestoresg1.beetalkmobile.com:8081/file/3d00ae7cc080976adf0278b3a688cbfd", "http://filestoresg1.beetalkmobile.com:8081/file/dd8cefe8435370642991f0e827ccb298"], "urls": [], "title": "\u6709\u96f2\u6797\u4eba\u53ef\u4ee5\u8a8d\u8b58\u55ce\uff1f"}, "threadStatus": 0, "regionId": 886, "barStatus": 0, "barId": 20, "postBy": {"utc": 1537784678000, "level": 2, "location": "\u53f0\u7063", "avatar": "http://filestoresg1.beetalkmobile.com:8081/file/3113490399744088886", "name": "\u5609\u8ed2\uff08\u6211\u662f\u4e09\u6027\u54e6\uff09"}, "id": 9695885}
