{"forum": {"content": "\u5c31\u662f\u660e\u5929\u4e86<br />0723<br />\u6211\u7684\u751f\u65e5<br />\u6709\u4eba\u9858\u610f\u7576\u6211\u7684\u5973\u670b\u53cb\u55ce\uff1f", "images": ["http://filestoresg1.beetalkmobile.com:8081/file/fad738e691069ca2e2f6ff46e9720b53", "http://filestoresg1.beetalkmobile.com:8081/file/7513bcbea9324c18926c51c7b7a4e50e"], "urls": [], "title": "\u9810\u795d\u751f\u65e5\u5feb\u6a02"}, "threadStatus": 0, "regionId": 886, "barStatus": 0, "barId": 205, "postBy": {"utc": 1532267979000, "level": 6, "location": "\u53f0\u7063", "avatar": "http://filestoresg1.beetalkmobile.com:8081/file/7900468234542157066", "name": "Wen-hao Chang"}, "id": 9071101}
