{"forum": {"content": "77/7/20\ud83d\ude0f<br />\u6b61\u8fce\u4e00\u8d77\u4ea4\u670b\u53cb\ud83d\udcaa", "images": ["http://filestoresg1.beetalkmobile.com:8081/file/c2fd89378777a73d6541a7031ac8b5ec"], "urls": [], "title": "\u6709\u4e03\u6708\u4efd\u5de8\u87f9\u5ea7\u8acb\u5165\u7559\u8a00\ud83d\udc40"}, "threadStatus": 0, "regionId": 886, "barStatus": 0, "barId": 765, "postBy": {"utc": 1531825001000, "level": 2, "location": "\u53f0\u5357\u5e02\u00b7\u53f0\u7063", "avatar": "http://filestoresg1.beetalkmobile.com:8081/file/-1020943819834623424", "name": "\u6960\u6e58\u6a9a"}, "id": 9023829}
