{"forum": {"content": "<br /><br />\u4e5f\u6c92\u751a\u9ebc\uff1f\u5c31\u7a81\u7136\ud83d\ude1b", "images": ["http://filestoresg1.beetalkmobile.com:8081/file/1503868a9ec5eea4e140c0d8fe18dbe6", "http://filestoresg1.beetalkmobile.com:8081/file/6b85ea669a128d08077199f18c2b9de4"], "urls": [], "title": "\u8822\u59b9\u53c8\u4f86\u4e86~\ud83d\ude02"}, "threadStatus": 0, "regionId": 886, "barStatus": 0, "barId": 782, "postBy": {"utc": 1533020061000, "level": 11, "location": "\u9ad8\u96c4\u5e02\u00b7\u53f0\u7063", "avatar": "http://filestoresg1.beetalkmobile.com:8081/file/-8851522694669157809", "name": "\u88ab\u5bf5\u58de\u3109\u760b\u7672\u9b3c\u5a9a \ud83d\udc7b\ud83d\udc3d\u5c01\u9748"}, "id": 9153430}
