{"forum": {"content": "\u55ae\u8eab\ud83d\udc36\u6c42\u597d\u53cb\u54e6", "images": ["http://filestoresg1.beetalkmobile.com:8081/file/236604cf817c1544126b6ce4c196896d"], "urls": [], "title": "\u8981\u95dc\u7248\u56c9 \u6c42\u597d\u53cb\u54e6"}, "threadStatus": 0, "regionId": 886, "barStatus": 0, "barId": 766, "postBy": {"utc": 1538009242000, "level": 1, "location": "", "avatar": "http://filestoresg1.beetalkmobile.com:8081/file/-2259456787130441424", "name": "\ud83c\udf7a\ud83c\udf7a"}, "id": 9721449}
