{"forum": {"content": "\u812b\u55ae\u662f\u53ef\u80fd\u7684\uff0c\u611b\u60c5\u7e3d\u662f\u4f86\u7684\u4ee4\u4eba\u63aa\u624b\u4e0d\u53ca\u5440\uff01<br />\u5927\u5bb6\u52a0\u6cb9\u54e6\uff01\ud83d\ude01<br /><br />\u9700\u8981\u5354\u52a9\u7684\u8acb\u4e0d\u8981\u627e\u6211\ud83d\ude02<br /><br />\uff08\u9019\u500b\u597d\u53cb\u662f\u5973\u7684~\u4e5f\u662f\u5728bt\u8a8d\u8b58\u7537\u751f\u7684\u54e6\uff01\u771f\u5fc3\u795d\u798f\ud83d\udc4d\ud83c\udffe\uff09", "images": ["http://filestoresg1.beetalkmobile.com:8081/file/f58ee2e34bfa25e3c15eaec37c576195", "http://filestoresg1.beetalkmobile.com:8081/file/1537c1fcfb5976e90ee918941b832dc3", "http://filestoresg1.beetalkmobile.com:8081/file/1a970ca38b67a2251b4335e600d8ba93", "http://filestoresg1.beetalkmobile.com:8081/file/d2206bac92077265f2157f32eb16e75f"], "urls": [], "title": "\u81f4\u6240\u6709\u55ae\u8eab\u5927\u53d4\ud83d\ude42"}, "threadStatus": 1, "regionId": 886, "barStatus": 0, "barId": 838, "postBy": {"utc": 1533713283000, "level": 11, "location": "", "avatar": "http://filestoresg1.beetalkmobile.com:8081/file/-7939659221037422079", "name": "\u50bb\u903c\u517c\u8870\u4ed4"}, "id": 9229166}
