{"forum": {"content": "\u6709\u500b\u7167\u7247\u4e0d\u77e5\u9053\u662f\u6d41\u661f\u9084\u662f\u5f57\u661f\u9084\u662f\u98db\u6a5f\u985e\u611f\u89ba\u4e0d\u600e\u50cf\u5f80\u4e0b\u53c8\u5f80\u4e0a\ud83d\ude05\ud83d\ude05\u4ed6\u883b\u539a\u7684<br />\u5269\u4e0b\u90fd\u662f\u5c0f\u62cd\u7684\u9280\u6cb3\u4e86\ud83d\ude09\ud83d\ude09<br />\u6bcf\u7576\u89aa\u773c\u73fe\u5834\u770b\u9280\u6cb3\u7e3d\u662f\u5fc3\u52d5<br />\u5fcd\u4e0d\u4f4f\u6d41\u4e0b\u4e00\u4e9b\u4e9b\u6dda\u6c34<br />\u771f\u7684\u5f88\u7f8e", "images": ["http://filestoresg1.beetalkmobile.com:8081/file/06af442bc930b45e62e79c358471f91e", "http://filestoresg1.beetalkmobile.com:8081/file/6a535d86266f84987a9547c2c107876c", "http://filestoresg1.beetalkmobile.com:8081/file/d69ba7e59950fb8fac5bf6253ed9c372", "http://filestoresg1.beetalkmobile.com:8081/file/6480e517b258243ab673642114d5a322", "http://filestoresg1.beetalkmobile.com:8081/file/40e5e4ce3fed07e65aa4850f5f6b471e", "http://filestoresg1.beetalkmobile.com:8081/file/eb0450dde46d8f167ad5d554f96ccce9"], "urls": [], "title": "\u6b66\u5dba\u7684\u5c0f\u62cd\ud83d\ude01"}, "threadStatus": 0, "regionId": 886, "barStatus": 0, "barId": 77, "postBy": {"utc": 1532119266000, "level": 2, "location": "", "avatar": "http://filestoresg1.beetalkmobile.com:8081/file/8337711035239541670", "name": "\u4fe1\uff5e\ud83d\ude01"}, "id": 9055439}
