{"forum": {"content": "\u6211\u76846\u5206XX<br />\u7834\u6ec5", "images": ["http://filestoresg1.beetalkmobile.com:8081/file/07a3c9fb635c4ef79b657c1211c996bb", "http://filestoresg1.beetalkmobile.com:8081/file/a3665581cee22f4ca4ad6a1852ed68be"], "urls": [], "title": "\u6b98\u5ff5"}, "threadStatus": 0, "regionId": 886, "barStatus": 0, "barId": 720, "postBy": {"utc": 1533564117000, "level": 2, "location": "\u53f0\u7063", "avatar": "http://filestoresg1.beetalkmobile.com:8081/file/-4595833242497482718", "name": "\u51d4\u4e42\u6f55\u6e9f"}, "id": 9212988}
