{"forum": {"content": "\u5922\u5230\u5abd\u62ff\u4e8610\u842c\u5143\u7d66\u6211\ud83e\udd23\ud83e\udd23\ud83e\udd23", "images": ["http://filestoresg1.beetalkmobile.com:8081/file/4d91b2daf9026dea2304f9f8f333fb3f"], "urls": [], "title": "\u9322\u62ff\u4f86\ud83e\udd17\ud83e\udd17\ud83e\udd17"}, "threadStatus": 0, "regionId": 886, "barStatus": 0, "barId": 758, "postBy": {"utc": 1537948317000, "level": 2, "location": "\u65b0\u5317\u5e02\u00b7\u53f0\u7063", "avatar": "http://filestoresg1.beetalkmobile.com:8081/file/4102480218548964067", "name": "\u80d6\u80d6\u599e"}, "id": 9714625}
