{"forum": {"content": "\u4eca\u5929\u65b0\u505a\u7684\u6708\u9905<br />\u4e0d\u904e\u8aaa\u771f\u7684<br />\u9084\u662f\u9700\u8981\u5728\u591a\u7df4\u7fd2<br />\u9019\u6a23\u7684\u6708\u9905\u4f60\u5011\u7d66\u5e7e\u5206\uff1f", "images": ["http://filestoresg1.beetalkmobile.com:8081/file/87ad4f61023323f6da9f78eb564aca8f", "http://filestoresg1.beetalkmobile.com:8081/file/3740dc0ce6032a530d8b295e81dedc46", "http://filestoresg1.beetalkmobile.com:8081/file/70e4614c2dfe19690511c132146b9b23"], "urls": [], "title": "\u9084\u6c92\u4e2d\u79cb\u5148\u505a\u6708\u9905\u5403"}, "threadStatus": 0, "regionId": 886, "barStatus": 0, "barId": 98, "postBy": {"utc": 1532714319000, "level": 2, "location": "", "avatar": "http://filestoresg1.beetalkmobile.com:8081/file/-5153192171217071103", "name": "LaLa"}, "id": 9119944}
