{"forum": {"content": "\u6211\u6709\u9ede\u8eab\u9ad8\u63a7\uff0c\u3002\u6709178\u4ee5\u4e0a\u559c\u6b61\u8089\u8089\u5973\u7684\u8981\u8a8d\u8b58\u5148\u7576\u670b\u53cb\u7684\u55ce\uff1f<br />              \u53f0\u5357", "images": ["http://filestoresg1.beetalkmobile.com:8081/file/a33eb2af1bbee36294485bbce97b5885", "http://filestoresg1.beetalkmobile.com:8081/file/af68bd8995754dd09e1aa9d6609eca68", "http://filestoresg1.beetalkmobile.com:8081/file/ce86ce865f07d6d17b82d5b1f241c4e0", "http://filestoresg1.beetalkmobile.com:8081/file/a23a0a0e4deba904e4df116d794ad9d1", "http://filestoresg1.beetalkmobile.com:8081/file/d35bfef19e54e08a85a4e45c72ca91cd"], "urls": [], "title": "\u4e0d\u60f3\u5728\u4e00\u500b\u4eba\uff0c\u60f3\u812b\u55ae\u560d\u3002\u3002"}, "threadStatus": 0, "regionId": 886, "barStatus": 0, "barId": 740, "postBy": {"utc": 1537075831000, "level": 5, "location": "\u53f0\u5357\u5e02\u00b7\u53f0\u7063", "avatar": "http://filestoresg1.beetalkmobile.com:8081/file/-8859424886268697258", "name": "\u738b\u66c9\u9756"}, "id": 9612237}
